q2mysql55_win_local/server.py
q2mysql55_win_local/version.py
q2mysql55_win_local/mysql55_files/my.ini
q2mysql55_win_local/mysql55_files/start.bat
q2mysql55_win_local/mysql55_files/stop.bat
q2mysql55_win_local/mysql55_files/bin/mysqladmin.exe
q2mysql55_win_local/mysql55_files/bin/mysqld.exe
q2mysql55_win_local/mysql55_files/data/mysql/columns_priv.MYD
q2mysql55_win_local/mysql55_files/data/mysql/columns_priv.MYI
q2mysql55_win_local/mysql55_files/data/mysql/columns_priv.frm
q2mysql55_win_local/mysql55_files/data/mysql/db.MYD
q2mysql55_win_local/mysql55_files/data/mysql/db.MYI
q2mysql55_win_local/mysql55_files/data/mysql/db.frm
q2mysql55_win_local/mysql55_files/data/mysql/event.MYD
q2mysql55_win_local/mysql55_files/data/mysql/event.MYI
q2mysql55_win_local/mysql55_files/data/mysql/event.frm
q2mysql55_win_local/mysql55_files/data/mysql/func.MYD
q2mysql55_win_local/mysql55_files/data/mysql/func.MYI
q2mysql55_win_local/mysql55_files/data/mysql/func.frm
q2mysql55_win_local/mysql55_files/data/mysql/general_log.CSM
q2mysql55_win_local/mysql55_files/data/mysql/general_log.CSV
q2mysql55_win_local/mysql55_files/data/mysql/general_log.frm
q2mysql55_win_local/mysql55_files/data/mysql/help_category.MYD
q2mysql55_win_local/mysql55_files/data/mysql/help_category.MYI
q2mysql55_win_local/mysql55_files/data/mysql/help_category.frm
q2mysql55_win_local/mysql55_files/data/mysql/help_keyword.MYD
q2mysql55_win_local/mysql55_files/data/mysql/help_keyword.MYI
q2mysql55_win_local/mysql55_files/data/mysql/help_keyword.frm
q2mysql55_win_local/mysql55_files/data/mysql/help_relation.MYD
q2mysql55_win_local/mysql55_files/data/mysql/help_relation.MYI
q2mysql55_win_local/mysql55_files/data/mysql/help_relation.frm
q2mysql55_win_local/mysql55_files/data/mysql/help_topic.MYD
q2mysql55_win_local/mysql55_files/data/mysql/help_topic.MYI
q2mysql55_win_local/mysql55_files/data/mysql/help_topic.frm
q2mysql55_win_local/mysql55_files/data/mysql/host.MYD
q2mysql55_win_local/mysql55_files/data/mysql/host.MYI
q2mysql55_win_local-0.1.9.dist-info/METADATA
q2mysql55_win_local-0.1.9.dist-info/WHEEL
q2mysql55_win_local-0.1.9.dist-info/top_level.txt
q2mysql55_win_local-0.1.9.dist-info/RECORD
