Metadata-Version: 2.4
Name: q2mysql55_win_local
Version: 0.1.9
Summary: Embedded local MySQL 5.5 server for portable Windows applications
Author: Andrei Puchko
License: MIT
Keywords: mysql,embedded-database,portable,windows,desktop-app,offline
Classifier: Operating System :: Microsoft :: Windows
Classifier: Programming Language :: Python :: 3
Classifier: Programming Language :: Python :: 3 :: Only
Classifier: Topic :: Database
Classifier: Topic :: Software Development :: Embedded Systems
Classifier: License :: OSI Approved :: MIT License
Classifier: Intended Audience :: Developers
Requires-Python: >=3.9
Requires-Dist: psutil; platform_system == "Windows"
